LICENSE
README.md
setup.py
PyCoke/__init__.py
PyCoke/core.py
PyCoke.egg-info/PKG-INFO
PyCoke.egg-info/SOURCES.txt
PyCoke.egg-info/dependency_links.txt
PyCoke.egg-info/top_level.txt